BetterNest/LabelParser.py
BetterNest/NestImage.py
BetterNest/WriteNst.py
BetterNest/__init__.py
BetterNest/nest_rawboards.py
BetterNest/return_nest_rawboards.py
ReadHop/ReadHop.py
ReadHop/SMBLabelParser.py
ReadHop/SMBReadHop.py
ReadHop/__init__.py
ReadHop/extract_all_processing.py
WriteHop/Contours.py
WriteHop/CustomCommands.py
WriteHop/Drilling.py
WriteHop/Machine.py
WriteHop/Milling.py
WriteHop/Nesting.py
WriteHop/WriteHop.py
WriteHop/__init__.py
nc_hops-0.2.6.dist-info/LICENSE
nc_hops-0.2.6.dist-info/METADATA
nc_hops-0.2.6.dist-info/WHEEL
nc_hops-0.2.6.dist-info/top_level.txt
nc_hops-0.2.6.dist-info/RECORD
