Metadata-Version: 2.1
Name: nc-hops
Version: 0.2.6
Summary: Hop file writer and reader
Home-page: https://github.com/apers0/nc-hops
Author: Nikola Brajic
Author-email: Nikola Brajic <nikolabrajic@proton.me>, Igor Pekovic <igor.pekovic95@gmail.com>, Aleksa Marceta <aleksa.marceta@gmail.com>
License: MIT
Project-URL: Homepage, https://github.com/apers0/nc-hops
Project-URL: Repository, https://github.com/apers0/nc-hops
Project-URL: Issues, https://github.com/apers0/nc-hops/issues
Project-URL: Download, https://pypi.org/project/nc-hops
Classifier: Programming Language :: Python :: 3
Classifier: Operating System :: OS Independent
Requires-Python: >=3.6
License-File: LICENSE
Requires-Dist: Pillow~=10.0.1
Requires-Dist: numpy~=1.26.0
Requires-Dist: setuptools~=70.0.0
Requires-Dist: smbprotocol~=1.13.0
Requires-Dist: chardet
Provides-Extra: dev
Requires-Dist: pytest; extra == "dev"
Requires-Dist: black; extra == "dev"
